{"minified":"composer/2.0","packages":{"october/all":[{"name":"october/all","description":"All common modules for October CMS","keywords":["core","october","october cms","all"],"homepage":"https://octobercms.com","version":"v3.4.0","version_normalized":"3.4.0.0","license":[],"authors":[{"name":"Alexey Bobkov","email":"aleksey.bobkov@gmail.com"},{"name":"Samuel Georges","email":"daftspunky@gmail.com"}],"source":{"url":"https://github.com/octoberrain/all.git","type":"git","reference":"139cf68cb3999363f3270e6e000ecdb24fb77157"},"dist":{"url":"https://api.github.com/repos/octoberrain/all/zipball/139cf68cb3999363f3270e6e000ecdb24fb77157","type":"zip","shasum":"","reference":"139cf68cb3999363f3270e6e000ecdb24fb77157"},"type":"library","time":"2023-06-30T01:42:41+00:00","require":{"october/system":"3.4.*","october/backend":"3.4.*","october/cms":"3.4.*","october/media":"3.4.*","october/editor":"3.4.*","october/tailor":"3.4.*"},"support":{"issues":"https://github.com/octoberrain/all/issues","source":"https://github.com/octoberrain/all/tree/v3.4.0"}},{"version":"v3.3.0","version_normalized":"3.3.0.0","source":{"url":"https://github.com/octoberrain/all.git","type":"git","reference":"2ca99be863f6d29801be2595134e4f7123b3acd8"},"dist":{"url":"https://api.github.com/repos/octoberrain/all/zipball/2ca99be863f6d29801be2595134e4f7123b3acd8","type":"zip","shasum":"","reference":"2ca99be863f6d29801be2595134e4f7123b3acd8"},"time":"2023-03-24T00:01:57+00:00","require":{"october/system":"3.3.*","october/backend":"3.3.*","october/cms":"3.3.*","october/media":"3.3.*","october/editor":"3.3.*","october/tailor":"3.3.*"},"support":{"issues":"https://github.com/octoberrain/all/issues","source":"https://github.com/octoberrain/all/tree/v3.3.0"}},{"version":"v3.2.0","version_normalized":"3.2.0.0","source":{"url":"https://github.com/octoberrain/all.git","type":"git","reference":"de31ec5c66fd0f7ec03644c5e62ff99e54ea6303"},"dist":{"url":"https://api.github.com/repos/octoberrain/all/zipball/de31ec5c66fd0f7ec03644c5e62ff99e54ea6303","type":"zip","shasum":"","reference":"de31ec5c66fd0f7ec03644c5e62ff99e54ea6303"},"time":"2023-01-12T00:00:35+00:00","require":{"october/system":"3.2.*","october/backend":"3.2.*","october/cms":"3.2.*","october/media":"3.2.*","october/editor":"3.2.*","october/tailor":"3.2.*"},"support":{"issues":"https://github.com/octoberrain/all/issues","source":"https://github.com/octoberrain/all/tree/v3.2.0"}},{"version":"v3.1.0","version_normalized":"3.1.0.0","source":{"url":"https://github.com/octoberrain/all.git","type":"git","reference":"0653be724c94a0164fc7c3192251f79a42002054"},"dist":{"url":"https://api.github.com/repos/octoberrain/all/zipball/0653be724c94a0164fc7c3192251f79a42002054","type":"zip","shasum":"","reference":"0653be724c94a0164fc7c3192251f79a42002054"},"time":"2022-10-05T04:44:25+00:00","require":{"october/system":"3.1.*","october/backend":"3.1.*","october/cms":"3.1.*","october/media":"3.1.*","october/editor":"3.1.*","october/tailor":"3.1.*"},"support":{"issues":"https://github.com/octoberrain/all/issues","source":"https://github.com/octoberrain/all/tree/v3.1.0"}},{"version":"v3.0.1","version_normalized":"3.0.1.0","source":{"url":"https://github.com/octoberrain/all.git","type":"git","reference":"d321033860618c10ff6f5269f802eb806c81e4e2"},"dist":{"url":"https://api.github.com/repos/octoberrain/all/zipball/d321033860618c10ff6f5269f802eb806c81e4e2","type":"zip","shasum":"","reference":"d321033860618c10ff6f5269f802eb806c81e4e2"},"time":"2022-05-05T23:52:17+00:00","require":{"october/system":"3.0.*","october/backend":"3.0.*","october/cms":"3.0.*","october/media":"3.0.*","october/editor":"3.0.*","october/tailor":"3.0.*"},"support":{"issues":"https://github.com/octoberrain/all/issues","source":"https://github.com/octoberrain/all/tree/v3.0.1"}},{"description":"All modules for October CMS","keywords":["core","october","october cms"],"version":"v3.0.0","version_normalized":"3.0.0.0","source":{"url":"https://github.com/octoberrain/all.git","type":"git","reference":"8aa620a0cbf6c878d7225fd2e27ac1ffbe6ec283"},"dist":{"url":"https://api.github.com/repos/octoberrain/all/zipball/8aa620a0cbf6c878d7225fd2e27ac1ffbe6ec283","type":"zip","shasum":"","reference":"8aa620a0cbf6c878d7225fd2e27ac1ffbe6ec283"},"time":"2022-02-01T01:05:31+00:00","require":{"october/system":"3.0.*","october/backend":"3.0.*","october/cms":"3.0.*","october/media":"3.0.*","october/editor":"3.0.*"},"support":{"issues":"https://github.com/octoberrain/all/issues","source":"https://github.com/octoberrain/all/tree/v3.0.0"}},{"version":"v2.2.0","version_normalized":"2.2.0.0","source":{"url":"https://github.com/octoberrain/all.git","type":"git","reference":"f6531b387651593b1ea63683043e5f9577b235d0"},"dist":{"url":"https://api.github.com/repos/octoberrain/all/zipball/f6531b387651593b1ea63683043e5f9577b235d0","type":"zip","shasum":"","reference":"f6531b387651593b1ea63683043e5f9577b235d0"},"time":"2022-03-02T00:36:15+00:00","require":{"october/system":"2.2.*","october/backend":"2.2.*","october/cms":"2.2.*","october/media":"2.2.*","october/editor":"2.2.*"},"support":{"issues":"https://github.com/octoberrain/all/issues","source":"https://github.com/octoberrain/all/tree/v2.2.0"}},{"version":"v2.1.0","version_normalized":"2.1.0.0","source":{"url":"https://github.com/octoberrain/all.git","type":"git","reference":"9c5792d2e42603ffbad6f3eceaa8b1f341c99176"},"dist":{"url":"https://api.github.com/repos/octoberrain/all/zipball/9c5792d2e42603ffbad6f3eceaa8b1f341c99176","type":"zip","shasum":"","reference":"9c5792d2e42603ffbad6f3eceaa8b1f341c99176"},"time":"2022-01-27T10:23:34+00:00","require":{"october/system":"2.1.*","october/backend":"2.1.*","october/cms":"2.1.*","october/media":"2.1.*","october/editor":"2.1.*"},"support":{"issues":"https://github.com/octoberrain/all/issues","source":"https://github.com/octoberrain/all/tree/v2.1.0"}},{"version":"v2.0.1","version_normalized":"2.0.1.0","source":{"url":"https://github.com/octoberrain/all.git","type":"git","reference":"783621844ffdfcd8e98f238121a54a8a99527801"},"dist":{"url":"https://api.github.com/repos/octoberrain/all/zipball/783621844ffdfcd8e98f238121a54a8a99527801","type":"zip","shasum":"","reference":"783621844ffdfcd8e98f238121a54a8a99527801"},"time":"2022-01-27T10:24:47+00:00","require":{"october/system":"2.0.*","october/backend":"2.0.*","october/cms":"2.0.*","october/media":"2.0.*","october/editor":"2.0.*"},"support":{"issues":"https://github.com/octoberrain/all/issues","source":"https://github.com/octoberrain/all/tree/v2.0.1"}},{"version":"v2.0.0","version_normalized":"2.0.0.0","source":{"url":"https://github.com/octoberrain/all.git","type":"git","reference":"901ac714a124cbf09705129a3d2ad265a65018d0"},"dist":{"url":"https://api.github.com/repos/octoberrain/all/zipball/901ac714a124cbf09705129a3d2ad265a65018d0","type":"zip","shasum":"","reference":"901ac714a124cbf09705129a3d2ad265a65018d0"},"time":"2021-08-03T23:14:07+00:00","require":{"october/system":"^2.0","october/backend":"^2.0","october/cms":"^2.0","october/media":"^2.0","october/editor":"^2.0"},"support":{"issues":"https://github.com/octoberrain/all/issues","source":"https://github.com/octoberrain/all/tree/v2.0.0"}}]},"security-advisories":[],"last-modified":"Fri, 30 Jun 2023 01:58:40 GMT"}